[
  {
    "id":1,
    "name":"Shivam",
    "no_of_codekata_probles_solved":100,
    "attendance":[
      {
        "attendance_date":ISODate("2021-10-15"),
        "status":"present"
      },
      {
        "attendance_date":ISODate("2021-10-20"),
        "status":"present"
      },
      {
        "attendance_date":ISODate("2021-10-25"),
        "status":"present"
      },
      {
        "attendance_date":ISODate("2021-10-30"),
        "status":"present"
      }
    ],
    "topics":["SQL","NoSQL","NodeJS"],
    "tasks":[
      {
        "task_name":"Creating Tables",
        "task_date":ISODate("2021-10-15"),
        "status":"Submitted"
      },
      {
        "task_name":"Joining Tables",
        "task_date":ISODate("2021-10-20"),
        "status":"Submitted"
      },
      {
        "task_name":"NoSQL basics",
        "task_date":ISODate("2021-10-25"),
        "status":"Submitted"
      },
      {
        "task_name":"NoSQL Advance",
        "task_date":ISODate("2021-10-30"),
        "status":"Submitted"
      }
    ],
    "Company_Drives_Appeared":["Delloite","Amazon","Chubb"]
  },
  {
    "id":2,
    "name":"John",
    "no_of_codekata_probles_solved":90,
    "attendance":[
      {
        "attendance_date":ISODate("2021-10-15"),
        "status":"present"
      },
      {
        "attendance_date":ISODate("2021-10-20"),
        "status":"absent"
      },
      {
        "attendance_date":ISODate("2021-10-25"),
        "status":"present"
      },
      {
        "attendance_date":ISODate("2021-10-30"),
        "status":"absent"
      }
    ],
    "topics":["SQL","NoSQL","Angular"],
    "tasks":[
      {
        "task_name":"Creating Tables",
        "task_date":ISODate("2021-10-15"),
        "status":"Submitted"
      },
      {
        "task_name":"Joining Tables",
        "task_date":ISODate("2021-10-20"),
        "status":"Not Submitted"
      },
      {
        "task_name":"NoSQL basics",
        "task_date":ISODate("2021-10-25"),
        "status":"Submitted"
      },
      {
        "task_name":"NoSQL Advance",
        "task_date":ISODate("2021-10-30"),
        "status":"Not Submitted"
      }
    ],
    "Company_Drives_Appeared":["Delloite","Amazon","Chubb"]
  },
  {
    "id":3,
    "name":"Ram",
    "no_of_codekata_probles_solved":95,
    "attendance":[
      {
        "attendance_date":ISODate("2021-10-15"),
        "status":"present"
      },
      {
        "attendance_date":ISODate("2021-10-20"),
        "status":"absent"
      },
      {
        "attendance_date":ISODate("2021-10-25"),
        "status":"absent"
      },
      {
        "attendance_date":ISODate("2021-10-30"),
        "status":"present"
      }
    ],
    "topics":["SQL","NoSQL","Python"],
    "tasks":[
      {
        "task_name":"Creating Tables",
        "task_date":ISODate("2021-10-15"),
        "status":"Submitted"
      },
      {
        "task_name":"Joining Tables",
        "task_date":ISODate("2021-10-20"),
        "status":"Submitted"
      },
      {
        "task_name":"NoSQL basics",
        "task_date":ISODate("2021-10-25"),
        "status":"Not Submitted"
      },
      {
        "task_name":"NoSQL Advance",
        "task_date":ISODate("2021-10-30"),
        "status":"Not Submitted"
      }
    ],
    "Company_Drives_Appeared":["Delloite","Amazon"]
  },
  {
    "id":4,
    "name":"Shyam",
    "no_of_codekata_probles_solved":92,
    "attendance":[
      {
        "attendance_date":ISODate("2021-10-15"),
        "status":"present"
      },
      {
        "attendance_date":ISODate("2021-10-20"),
        "status":"absent"
      },
      {
        "attendance_date":ISODate("2021-10-25"),
        "status":"absent"
      },
      {
        "attendance_date":ISODate("2021-10-30"),
        "status":"absent"
      }
    ],
    "topics":["SQL","NoSQL","Mean"],
    "tasks":[
      {
        "task_name":"Creating Tables",
        "task_date":ISODate("2021-10-15"),
        "status":"Submitted"
      },
      {
        "task_name":"Joining Tables",
        "task_date":ISODate("2021-10-20"),
        "status":"Submitted"
      },
      {
        "task_name":"NoSQL basics",
        "task_date":ISODate("2021-10-25"),
        "status":"Not Submitted"
      },
      {
        "task_name":"NoSQL Advance",
        "task_date":ISODate("2021-10-30"),
        "status":"Not Submitted"
      }
    ],
    "Company_Drives_Appeared":["Google","Microsoft"]
  }
]
